AUTHORS
ChangeLog
LICENSE
README.rst
requirements.txt
setup.cfg
setup.py
helga_grafana/__init__.py
helga_grafana/webhooks.py
helga_grafana.egg-info/PKG-INFO
helga_grafana.egg-info/SOURCES.txt
helga_grafana.egg-info/dependency_links.txt
helga_grafana.egg-info/entry_points.txt
helga_grafana.egg-info/not-zip-safe
helga_grafana.egg-info/pbr.json
helga_grafana.egg-info/requires.txt
helga_grafana.egg-info/top_level.txt