Metadata-Version: 1.1
Name: helga-grafana
Version: 0.1.1
Summary: Plugin for Helga to receive Grafana webhook alerts
Home-page: https://github.com/ianw/helga-grafana
Author: Ian Wienand
Author-email: ian@wienand.org
License: UNKNOWN
Platform: UNKNOWN
Classifier: Intended Audience :: Information Technology
Classifier: Intended Audience :: System Administrators
Classifier: License :: OSI Approved :: Apache Software License
Classifier: Operating System :: POSIX :: Linux
Classifier: Programming Language :: Python :: 2
Classifier: Programming Language :: Python :: 2.7
